starwhale_bootstrap/__init__.py
starwhale_bootstrap/cmd.py
starwhale_bootstrap/default.py
starwhale_bootstrap/deploy.py
starwhale_bootstrap/playbook/bootstrap.yaml
starwhale_bootstrap/playbook/roles/agent/tasks/main.yaml
starwhale_bootstrap/playbook/roles/controller/tasks/main.yaml
starwhale_bootstrap/playbook/roles/minio/tasks/main.yaml
starwhale_bootstrap/playbook/roles/mysql/tasks/main.yaml
starwhale_bootstrap/playbook/roles/nexus/tasks/main.yaml
starwhale_bootstrap-0.2.2b6.dist-info/METADATA
starwhale_bootstrap-0.2.2b6.dist-info/WHEEL
starwhale_bootstrap-0.2.2b6.dist-info/entry_points.txt
starwhale_bootstrap-0.2.2b6.dist-info/top_level.txt
starwhale_bootstrap-0.2.2b6.dist-info/RECORD
