Metadata-Version: 2.1
Name: starwhale-bootstrap
Version: 0.2.2b6
Summary: MLOps Platform
Home-page: https://github.com/star-whale/starwhale
Author: Starwhale Team
Author-email: developer@starwhale.ai
License: Apache-2.0
Keywords: MLOps AI
Platform: UNKNOWN
Classifier: Programming Language :: Python :: 3
Classifier: License :: Free for non-commercial use
Classifier: Operating System :: OS Independent
Requires-Dist: ansible
Requires-Dist: ansible-runner
Requires-Dist: click
